yamlsettings_s3.py
yamlsettings_s3-1.0.0.dist-info/METADATA
yamlsettings_s3-1.0.0.dist-info/RECORD
yamlsettings_s3-1.0.0.dist-info/WHEEL
yamlsettings_s3-1.0.0.dist-info/entry_points.txt
yamlsettings_s3-1.0.0.dist-info/top_level.txt
